[ {
  "id" : "3ed16d72-decf-80be-0d87-60bb550e7fb0",
  "name" : "field_group",
  "display_width" : null,
  "label" : "Card group",
  "required" : false,
  "locked" : false,
  "occurrence" : {
    "min" : null,
    "max" : null,
    "sorting_label_field" : null,
    "default" : null
  },
  "children" : [ {
    "id" : "133bddfe-b93a-5a82-0aa8-fd315731e5b6",
    "name" : "image_field",
    "display_width" : null,
    "label" : "Image",
    "required" : false,
    "locked" : false,
    "responsive" : true,
    "resizable" : true,
    "show_loading" : false,
    "type" : "image",
    "default" : {
      "size_type" : "auto",
      "src" : "",
      "alt" : null,
      "loading" : "lazy"
    }
  }, {
    "id" : "5f3a821c-6cb0-58aa-d49e-ce3c18594ff9",
    "name" : "text_field",
    "display_width" : null,
    "label" : "Text",
    "help_text" : "This is the heading",
    "required" : false,
    "locked" : false,
    "validation_regex" : "",
    "allow_new_line" : false,
    "show_emoji_picker" : false,
    "type" : "text",
    "default" : "Heading"
  }, {
    "id" : "66528611-a56c-b02c-9c5a-f5a4ecc3443f",
    "name" : "richtext_field",
    "display_width" : null,
    "label" : "Rich text",
    "help_text" : "This is the body text",
    "required" : false,
    "locked" : false,
    "type" : "richtext"
  }, {
    "id" : "de7c2fb3-35cc-0767-9817-b36f51f2ae2a",
    "name" : "link_field",
    "display_width" : null,
    "label" : "Link",
    "required" : false,
    "locked" : false,
    "supported_types" : [ "EXTERNAL", "CONTENT", "FILE", "EMAIL_ADDRESS", "BLOG", "CALL_TO_ACTION", "PHONE_NUMBER", "WHATSAPP_NUMBER", "PAYMENT" ],
    "show_advanced_rel_options" : false,
    "type" : "link",
    "default" : {
      "url" : {
        "content_id" : null,
        "type" : "EXTERNAL",
        "href" : ""
      },
      "open_in_new_tab" : false,
      "no_follow" : false
    }
  } ],
  "tab" : "CONTENT",
  "expanded" : false,
  "type" : "group",
  "default" : {
    "image_field" : {
      "size_type" : "auto",
      "src" : "",
      "alt" : null,
      "loading" : "lazy"
    },
    "text_field" : "Heading",
    "link_field" : {
      "url" : {
        "content_id" : null,
        "type" : "EXTERNAL",
        "href" : ""
      },
      "open_in_new_tab" : false,
      "no_follow" : false
    }
  }
} ]